{

    "affinities": [{
        "_id": "YYMmNDm2mTWnAf8Hx",
        "helperId": "aupdNzYu8WmNEi4e5",
        "helpeeId": "9gcjpT4daYZmZDi2F",
        "groupId": "sM3z5FkZfsABqcj3g",
        "value": -1
    },
    {
        "_id": "KXCc6Qj4CxLCoMgPr",
        "helperId": "6Yv3ARWJQMWtFKgnN",
        "helpeeId": "PavTL8zD9664wvtfB",
        "groupId": "sM3z5FkZfsABqcj3g",
        "value": -1
    },
    {
        "_id": "styqSf6yTbQeXk2Q9",
        "helperId": "aupdNzYu8WmNEi4e5",
        "helpeeId": "N3LsK5NJeKm8PkBx8",
        "groupId": "sM3z5FkZfsABqcj3g",
        "value": -1
    },
    {
        "_id": "e3jaqoPkoNBsM6mqz",
        "helperId": "PavTL8zD9664wvtfB",
        "helpeeId": "nDHZGzczDWyqvyFhp",
        "groupId": "sM3z5FkZfsABqcj3g",
        "value": 1
    },
    {
        "_id": "trQPPtFLWaHsQ5CnE",
        "helperId": "u6DrqFSvdZnWDgjz8",
        "helpeeId": "9zFPYRJQ5KnGTcnMr",
        "groupId": "sM3z5FkZfsABqcj3g",
        "value": 0.33
    },
    {
        "_id": "FwdP2PoggZLYajso8",
        "helperId": "XjH8WJxEXFgTwdi3o",
        "helpeeId": "afyZT6q2HepoCS76m",
        "groupId": "sM3z5FkZfsABqcj3g",
        "value": 0.33
    },
    {
        "_id": "NcotsgTRmHuox4K5P",
        "helperId": "afyZT6q2HepoCS76m",
        "helpeeId": "6rZbYn3cbQ9KNLRM5",
        "groupId": "sM3z5FkZfsABqcj3g",
        "value": 0.66
    },
    {
        "_id": "zEpghs3Tchpkmr8YR",
        "helperId": "yLoAP6fd9WbQQPyhb",
        "helpeeId": "9zFPYRJQ5KnGTcnMr",
        "groupId": "sM3z5FkZfsABqcj3g",
        "value": 1
    },
    {
        "_id": "9Qx8KHgS59MPdYjkk",
        "helperId": "9zFPYRJQ5KnGTcnMr",
        "helpeeId": "dZ23LYG2G42mY3NAf",
        "groupId": "sM3z5FkZfsABqcj3g",
        "value": -1
    },
    {
        "_id": "XWbPZnKsEPqpavRnd",
        "helperId": "nDHZGzczDWyqvyFhp",
        "helpeeId": "N3LsK5NJeKm8PkBx8",
        "groupId": "sM3z5FkZfsABqcj3g",
        "value": -1
    },
    {
        "_id": "9XsqDRyMbmAmRYuYi",
        "helperId": "EDEFWcagLwCfXP5Jg",
        "helpeeId": "N3LsK5NJeKm8PkBx8",
        "groupId": "sM3z5FkZfsABqcj3g",
        "value": -1
    },
    {
        "_id": "68bMGofzW5wezxqLj",
        "helperId": "dZ23LYG2G42mY3NAf",
        "helpeeId": "XjH8WJxEXFgTwdi3o",
        "groupId": "sM3z5FkZfsABqcj3g",
        "value": -1
    },
    {
        "_id": "y2PWtHknh479fadgK",
        "helperId": "iwonAbZGTP9j7BFe3",
        "helpeeId": "6rZbYn3cbQ9KNLRM5",
        "groupId": "sM3z5FkZfsABqcj3g",
        "value": 1
    },
    {
        "_id": "xJuxAZ35tC6mPJpTw",
        "helperId": "nDHZGzczDWyqvyFhp",
        "helpeeId": "yLoAP6fd9WbQQPyhb",
        "groupId": "sM3z5FkZfsABqcj3g",
        "value": -1
    },
    {
        "_id": "dXiKQAWDuPoqPXeEs",
        "helperId": "nDHZGzczDWyqvyFhp",
        "helpeeId": "XjH8WJxEXFgTwdi3o",
        "groupId": "sM3z5FkZfsABqcj3g",
        "value": -1
    },
    {
        "_id": "GXF4qa4vidqRduNua",
        "helperId": "6rZbYn3cbQ9KNLRM5",
        "helpeeId": "9zFPYRJQ5KnGTcnMr",
        "groupId": "sM3z5FkZfsABqcj3g",
        "value": 0
    },
    {
        "_id": "u3aXcqyPSqgS6Zv6L",
        "helperId": "XjH8WJxEXFgTwdi3o",
        "helpeeId": "9zFPYRJQ5KnGTcnMr",
        "groupId": "sM3z5FkZfsABqcj3g",
        "value": 0.66
    },
    {
        "_id": "7kCvK2qYcpNEPrqjG",
        "helperId": "6Yv3ARWJQMWtFKgnN",
        "helpeeId": "iwonAbZGTP9j7BFe3",
        "groupId": "sM3z5FkZfsABqcj3g",
        "value": -1
    },
    {
        "_id": "koDsJSCF7iWbwrKbQ",
        "helperId": "9zFPYRJQ5KnGTcnMr",
        "helpeeId": "aupdNzYu8WmNEi4e5",
        "groupId": "sM3z5FkZfsABqcj3g",
        "value": 0
    },
    {
        "_id": "o7ZLibMkocHfZGP54",
        "helperId": "6rZbYn3cbQ9KNLRM5",
        "helpeeId": "afyZT6q2HepoCS76m",
        "groupId": "sM3z5FkZfsABqcj3g",
        "value": 0
    },
    {
        "_id": "X7cDMXdYuad8A2CeP",
        "helperId": "dZ23LYG2G42mY3NAf",
        "helpeeId": "9gcjpT4daYZmZDi2F",
        "groupId": "sM3z5FkZfsABqcj3g",
        "value": -1
    },
    {
        "_id": "Y2jrbjETPwrhBsSBJ",
        "helperId": "iwonAbZGTP9j7BFe3",
        "helpeeId": "PavTL8zD9664wvtfB",
        "groupId": "sM3z5FkZfsABqcj3g",
        "value": -1
    },
    {
        "_id": "NE8qBpHoeaCxG5yPP",
        "helperId": "nDHZGzczDWyqvyFhp",
        "helpeeId": "u6DrqFSvdZnWDgjz8",
        "groupId": "sM3z5FkZfsABqcj3g",
        "value": -1
    },
    {
        "_id": "FFBKm27ChGE7dNsjJ",
        "helperId": "nDHZGzczDWyqvyFhp",
        "helpeeId": "9gcjpT4daYZmZDi2F",
        "groupId": "sM3z5FkZfsABqcj3g",
        "value": -1
    },
    {
        "_id": "qWdECfSMw34yyos7n",
        "helperId": "N3LsK5NJeKm8PkBx8",
        "helpeeId": "9zFPYRJQ5KnGTcnMr",
        "groupId": "sM3z5FkZfsABqcj3g",
        "value": 1
    },
    {
        "_id": "DMMiJsXEfDbbywZF9",
        "helperId": "XjH8WJxEXFgTwdi3o",
        "helpeeId": "EDEFWcagLwCfXP5Jg",
        "groupId": "sM3z5FkZfsABqcj3g",
        "value": 0.33
    },
    {
        "_id": "5v2RLbJfRifyhrhY2",
        "helperId": "dZ23LYG2G42mY3NAf",
        "helpeeId": "u6DrqFSvdZnWDgjz8",
        "groupId": "sM3z5FkZfsABqcj3g",
        "value": -1
    },
    {
        "_id": "mQwsmJ2B6xsLXXqf4",
        "helperId": "6Yv3ARWJQMWtFKgnN",
        "helpeeId": "6rZbYn3cbQ9KNLRM5",
        "groupId": "sM3z5FkZfsABqcj3g",
        "value": 0.33
    },
    {
        "_id": "mWQcwyysPkz24a4GC",
        "helperId": "u6DrqFSvdZnWDgjz8",
        "helpeeId": "EDEFWcagLwCfXP5Jg",
        "groupId": "sM3z5FkZfsABqcj3g",
        "value": 0.66
    },
    {
        "_id": "txMHaAAePkP3rERs7",
        "helperId": "iwonAbZGTP9j7BFe3",
        "helpeeId": "aupdNzYu8WmNEi4e5",
        "groupId": "sM3z5FkZfsABqcj3g",
        "value": 1
    },
    {
        "_id": "3nfDGNMopCMjYtGQe",
        "helperId": "9zFPYRJQ5KnGTcnMr",
        "helpeeId": "PavTL8zD9664wvtfB",
        "groupId": "sM3z5FkZfsABqcj3g",
        "value": 0.66
    },
    {
        "_id": "PaDPdNyy4PQZ3orQc",
        "helperId": "XjH8WJxEXFgTwdi3o",
        "helpeeId": "nDHZGzczDWyqvyFhp",
        "groupId": "sM3z5FkZfsABqcj3g",
        "value": 0.66
    },
    {
        "_id": "GcGFPvFZHwzyfTJRo",
        "helperId": "N3LsK5NJeKm8PkBx8",
        "helpeeId": "nDHZGzczDWyqvyFhp",
        "groupId": "sM3z5FkZfsABqcj3g",
        "value": 1
    },
    {
        "_id": "RBEDLhHXNYdijm3qZ",
        "helperId": "dZ23LYG2G42mY3NAf",
        "helpeeId": "N3LsK5NJeKm8PkBx8",
        "groupId": "sM3z5FkZfsABqcj3g",
        "value": -1
    },
    {
        "_id": "Sbcn4Q6jh5sHYAQA4",
        "helperId": "u6DrqFSvdZnWDgjz8",
        "helpeeId": "nDHZGzczDWyqvyFhp",
        "groupId": "sM3z5FkZfsABqcj3g",
        "value": 0.33
    },
    {
        "_id": "wi5Hsvu8WBikCWQdr",
        "helperId": "6Yv3ARWJQMWtFKgnN",
        "helpeeId": "afyZT6q2HepoCS76m",
        "groupId": "sM3z5FkZfsABqcj3g",
        "value": -1
    },
    {
        "_id": "yvX2MTLLg5G3k3kRt",
        "helperId": "PavTL8zD9664wvtfB",
        "helpeeId": "dZ23LYG2G42mY3NAf",
        "groupId": "sM3z5FkZfsABqcj3g",
        "value": 0.33
    },
    {
        "_id": "urFZxQwiTy4wQcigv",
        "helperId": "iwonAbZGTP9j7BFe3",
        "helpeeId": "N3LsK5NJeKm8PkBx8",
        "groupId": "sM3z5FkZfsABqcj3g",
        "value": -1
    },
    {
        "_id": "W8CrNL9YZwWAA76qC",
        "helperId": "XjH8WJxEXFgTwdi3o",
        "helpeeId": "dZ23LYG2G42mY3NAf",
        "groupId": "sM3z5FkZfsABqcj3g",
        "value": 0.33
    },
    {
        "_id": "Z8hLFu65b6A9EfzMt",
        "helperId": "iwonAbZGTP9j7BFe3",
        "helpeeId": "yLoAP6fd9WbQQPyhb",
        "groupId": "sM3z5FkZfsABqcj3g",
        "value": 0.66
    },
    {
        "_id": "J23C3ENDinkvKngTc",
        "helperId": "6Yv3ARWJQMWtFKgnN",
        "helpeeId": "N3LsK5NJeKm8PkBx8",
        "groupId": "sM3z5FkZfsABqcj3g",
        "value": -1
    },
    {
        "_id": "ZZXdNpL8x7ZqNBGgt",
        "helperId": "N3LsK5NJeKm8PkBx8",
        "helpeeId": "EDEFWcagLwCfXP5Jg",
        "groupId": "sM3z5FkZfsABqcj3g",
        "value": 0
    },
    {
        "_id": "4LGj2ztruxjS6y2T4",
        "helperId": "N3LsK5NJeKm8PkBx8",
        "helpeeId": "dZ23LYG2G42mY3NAf",
        "groupId": "sM3z5FkZfsABqcj3g",
        "value": 1
    },
    {
        "_id": "4w48FBhCSZZ3XaFxE",
        "helperId": "6Yv3ARWJQMWtFKgnN",
        "helpeeId": "yLoAP6fd9WbQQPyhb",
        "groupId": "sM3z5FkZfsABqcj3g",
        "value": 1
    },
    {
        "_id": "Xb6WJXSySyEa5aHAg",
        "helperId": "iwonAbZGTP9j7BFe3",
        "helpeeId": "XjH8WJxEXFgTwdi3o",
        "groupId": "sM3z5FkZfsABqcj3g",
        "value": 0
    },
    {
        "_id": "ujW2dZJEd8fptvWYt",
        "helperId": "yLoAP6fd9WbQQPyhb",
        "helpeeId": "EDEFWcagLwCfXP5Jg",
        "groupId": "sM3z5FkZfsABqcj3g",
        "value": 0.66
    },
    {
        "_id": "ax4C72xaD7ugPftka",
        "helperId": "u6DrqFSvdZnWDgjz8",
        "helpeeId": "dZ23LYG2G42mY3NAf",
        "groupId": "sM3z5FkZfsABqcj3g",
        "value": 0
    },
    {
        "_id": "zA4PDoNrWFxhHCbmc",
        "helperId": "9zFPYRJQ5KnGTcnMr",
        "helpeeId": "iwonAbZGTP9j7BFe3",
        "groupId": "sM3z5FkZfsABqcj3g",
        "value": 0
    },
    {
        "_id": "sbYPLSGzbpNbZvN4t",
        "helperId": "yLoAP6fd9WbQQPyhb",
        "helpeeId": "nDHZGzczDWyqvyFhp",
        "groupId": "sM3z5FkZfsABqcj3g",
        "value": 0.66
    },
    {
        "_id": "8tR9DYrvM2CkaBMab",
        "helperId": "6Yv3ARWJQMWtFKgnN",
        "helpeeId": "XjH8WJxEXFgTwdi3o",
        "groupId": "sM3z5FkZfsABqcj3g",
        "value": -1
    },
    {
        "_id": "kDZpCH46NdXaNPRNh",
        "helperId": "afyZT6q2HepoCS76m",
        "helpeeId": "u6DrqFSvdZnWDgjz8",
        "groupId": "sM3z5FkZfsABqcj3g",
        "value": 0.66
    },
    {
        "_id": "cc529PPF7GmqySNBS",
        "helperId": "EDEFWcagLwCfXP5Jg",
        "helpeeId": "zn7csxv966BaTnhrg",
        "groupId": "sM3z5FkZfsABqcj3g",
        "value": -1
    },
    {
        "_id": "S3ZKuiAbT5WLTmXyC",
        "helperId": "aupdNzYu8WmNEi4e5",
        "helpeeId": "zn7csxv966BaTnhrg",
        "groupId": "sM3z5FkZfsABqcj3g",
        "value": -1
    },
    {
        "_id": "bAigoEBdLRMkCbhqc",
        "helperId": "9zFPYRJQ5KnGTcnMr",
        "helpeeId": "6rZbYn3cbQ9KNLRM5",
        "groupId": "sM3z5FkZfsABqcj3g",
        "value": 1
    },
    {
        "_id": "dNnn4W9tYDnJiY7ew",
        "helperId": "6Yv3ARWJQMWtFKgnN",
        "helpeeId": "9gcjpT4daYZmZDi2F",
        "groupId": "sM3z5FkZfsABqcj3g",
        "value": -1
    },
    {
        "_id": "evQnC3mNZiGjcn7ub",
        "helperId": "u6DrqFSvdZnWDgjz8",
        "helpeeId": "aupdNzYu8WmNEi4e5",
        "groupId": "sM3z5FkZfsABqcj3g",
        "value": -1
    },
    {
        "_id": "KK6y7nsfPhSEs9Cev",
        "helperId": "yLoAP6fd9WbQQPyhb",
        "helpeeId": "dZ23LYG2G42mY3NAf",
        "groupId": "sM3z5FkZfsABqcj3g",
        "value": 1
    },
    {
        "_id": "X7RcJsuxmXggibNpK",
        "helperId": "6Yv3ARWJQMWtFKgnN",
        "helpeeId": "u6DrqFSvdZnWDgjz8",
        "groupId": "sM3z5FkZfsABqcj3g",
        "value": 1
    },
    {
        "_id": "awpAtizd94AW4sese",
        "helperId": "9zFPYRJQ5KnGTcnMr",
        "helpeeId": "6Yv3ARWJQMWtFKgnN",
        "groupId": "sM3z5FkZfsABqcj3g",
        "value": 0.66
    },
    {
        "_id": "gupEthqYHHQcL7nMn",
        "helperId": "6rZbYn3cbQ9KNLRM5",
        "helpeeId": "aupdNzYu8WmNEi4e5",
        "groupId": "sM3z5FkZfsABqcj3g",
        "value": -1
    },
    {
        "_id": "ZyHMz4AaqLL4ec6qf",
        "helperId": "XjH8WJxEXFgTwdi3o",
        "helpeeId": "PavTL8zD9664wvtfB",
        "groupId": "sM3z5FkZfsABqcj3g",
        "value": 0.33
    },
    {
        "_id": "qSapoDpzbLJ8En9XN",
        "helperId": "6rZbYn3cbQ9KNLRM5",
        "helpeeId": "PavTL8zD9664wvtfB",
        "groupId": "sM3z5FkZfsABqcj3g",
        "value": -1
    },
    {
        "_id": "MQTDcidPXaWxRQPX3",
        "helperId": "yLoAP6fd9WbQQPyhb",
        "helpeeId": "aupdNzYu8WmNEi4e5",
        "groupId": "sM3z5FkZfsABqcj3g",
        "value": 0.66
    },
    {
        "_id": "RdvvNfAWopa9iht9H",
        "helperId": "N3LsK5NJeKm8PkBx8",
        "helpeeId": "PavTL8zD9664wvtfB",
        "groupId": "sM3z5FkZfsABqcj3g",
        "value": 0
    },
    {
        "_id": "g6DsG2AzZBXAsWnKk",
        "helperId": "u6DrqFSvdZnWDgjz8",
        "helpeeId": "PavTL8zD9664wvtfB",
        "groupId": "sM3z5FkZfsABqcj3g",
        "value": 0.33
    },
    {
        "_id": "4wsmsgy2Zsmb943Dr",
        "helperId": "yLoAP6fd9WbQQPyhb",
        "helpeeId": "9gcjpT4daYZmZDi2F",
        "groupId": "sM3z5FkZfsABqcj3g",
        "value": -1
    },
    {
        "_id": "2Zof9WEYv3soGMCQb",
        "helperId": "XjH8WJxEXFgTwdi3o",
        "helpeeId": "CQhpnQnrAQMZhD9tM",
        "groupId": "sM3z5FkZfsABqcj3g",
        "value": 0
    },
    {
        "_id": "TW8bYejN8b8ANCkNq",
        "helperId": "9zFPYRJQ5KnGTcnMr",
        "helpeeId": "CQhpnQnrAQMZhD9tM",
        "groupId": "sM3z5FkZfsABqcj3g",
        "value": 0.66
    },
    {
        "_id": "3LFXBnpRyWDzbWWFn",
        "helperId": "aupdNzYu8WmNEi4e5",
        "helpeeId": "CQhpnQnrAQMZhD9tM",
        "groupId": "sM3z5FkZfsABqcj3g",
        "value": -1
    },
    {
        "_id": "iW5o8xaiqwRyPjw8j",
        "helperId": "N3LsK5NJeKm8PkBx8",
        "helpeeId": "aupdNzYu8WmNEi4e5",
        "groupId": "sM3z5FkZfsABqcj3g",
        "value": 0.66
    },
    {
        "_id": "DSxwphLexhsYa9wZm",
        "helperId": "N3LsK5NJeKm8PkBx8",
        "helpeeId": "afyZT6q2HepoCS76m",
        "groupId": "sM3z5FkZfsABqcj3g",
        "value": 0.33
    },
    {
        "_id": "XLMmAYA75PZYdvGs6",
        "helperId": "u6DrqFSvdZnWDgjz8",
        "helpeeId": "XjH8WJxEXFgTwdi3o",
        "groupId": "sM3z5FkZfsABqcj3g",
        "value": -1
    },
    {
        "_id": "uQgqipZ4tB7ouhbJ8",
        "helperId": "9gcjpT4daYZmZDi2F",
        "helpeeId": "dZ23LYG2G42mY3NAf",
        "groupId": "sM3z5FkZfsABqcj3g",
        "value": 0.33
    },
    {
        "_id": "hGkwWr7ynAp2PTY4r",
        "helperId": "yLoAP6fd9WbQQPyhb",
        "helpeeId": "XjH8WJxEXFgTwdi3o",
        "groupId": "sM3z5FkZfsABqcj3g",
        "value": 1
    },
    {
        "_id": "pha2v9Q8npv2i5FXH",
        "helperId": "afyZT6q2HepoCS76m",
        "helpeeId": "zn7csxv966BaTnhrg",
        "groupId": "sM3z5FkZfsABqcj3g",
        "value": 1
    },
    {
        "_id": "X5fmXKcEQ2xGdc5G9",
        "helperId": "yLoAP6fd9WbQQPyhb",
        "helpeeId": "N3LsK5NJeKm8PkBx8",
        "groupId": "sM3z5FkZfsABqcj3g",
        "value": 1
    },
    {
        "_id": "hWoDqDWBcn5z86bhN",
        "helperId": "6rZbYn3cbQ9KNLRM5",
        "helpeeId": "CQhpnQnrAQMZhD9tM",
        "groupId": "sM3z5FkZfsABqcj3g",
        "value": 0
    },
    {
        "_id": "WsMYLrPJNqEEX9Xwg",
        "helperId": "PavTL8zD9664wvtfB",
        "helpeeId": "iwonAbZGTP9j7BFe3",
        "groupId": "sM3z5FkZfsABqcj3g",
        "value": -1
    },
    {
        "_id": "ANo6eBusYPPrxghPa",
        "helperId": "u6DrqFSvdZnWDgjz8",
        "helpeeId": "yLoAP6fd9WbQQPyhb",
        "groupId": "sM3z5FkZfsABqcj3g",
        "value": 0.66
    },
    {
        "_id": "x8jBzNsJB7bu3Sq8u",
        "helperId": "PavTL8zD9664wvtfB",
        "helpeeId": "6rZbYn3cbQ9KNLRM5",
        "groupId": "sM3z5FkZfsABqcj3g",
        "value": -1
    },
    {
        "_id": "84MmtE7CYokgiJBFj",
        "helperId": "XjH8WJxEXFgTwdi3o",
        "helpeeId": "6rZbYn3cbQ9KNLRM5",
        "groupId": "sM3z5FkZfsABqcj3g",
        "value": 0.33
    },
    {
        "_id": "PyvbD5frQ7r2ToRct",
        "helperId": "PavTL8zD9664wvtfB",
        "helpeeId": "6Yv3ARWJQMWtFKgnN",
        "groupId": "sM3z5FkZfsABqcj3g",
        "value": 1
    },
    {
        "_id": "LbN4u2MtjpLCa7kDX",
        "helperId": "yLoAP6fd9WbQQPyhb",
        "helpeeId": "zn7csxv966BaTnhrg",
        "groupId": "sM3z5FkZfsABqcj3g",
        "value": 0.66
    },
    {
        "_id": "CL6bnHSd3eTv97qTR",
        "helperId": "u6DrqFSvdZnWDgjz8",
        "helpeeId": "N3LsK5NJeKm8PkBx8",
        "groupId": "sM3z5FkZfsABqcj3g",
        "value": 0.66
    },
    {
        "_id": "SDCoGpJvEZG9JEBsL",
        "helperId": "9gcjpT4daYZmZDi2F",
        "helpeeId": "aupdNzYu8WmNEi4e5",
        "groupId": "sM3z5FkZfsABqcj3g",
        "value": 0.66
    },
    {
        "_id": "XTmPjFaWKxA2geech",
        "helperId": "9gcjpT4daYZmZDi2F",
        "helpeeId": "PavTL8zD9664wvtfB",
        "groupId": "sM3z5FkZfsABqcj3g",
        "value": 0
    },
    {
        "_id": "Wf6ixLErHfJeBc8KK",
        "helperId": "u6DrqFSvdZnWDgjz8",
        "helpeeId": "zn7csxv966BaTnhrg",
        "groupId": "sM3z5FkZfsABqcj3g",
        "value": 0.66
    },
    {
        "_id": "hXBTGFu5NRcP4r7hQ",
        "helperId": "yLoAP6fd9WbQQPyhb",
        "helpeeId": "CQhpnQnrAQMZhD9tM",
        "groupId": "sM3z5FkZfsABqcj3g",
        "value": 1
    },
    {
        "_id": "WkTc5GhaK9kWB6Z29",
        "helperId": "afyZT6q2HepoCS76m",
        "helpeeId": "CQhpnQnrAQMZhD9tM",
        "groupId": "sM3z5FkZfsABqcj3g",
        "value": 1
    },
    {
        "_id": "efbidELpoXZz9sbZZ",
        "helperId": "u6DrqFSvdZnWDgjz8",
        "helpeeId": "CQhpnQnrAQMZhD9tM",
        "groupId": "sM3z5FkZfsABqcj3g",
        "value": -1
    },
    {
        "_id": "wcJpAEBpcgN5yKrPF",
        "helperId": "9gcjpT4daYZmZDi2F",
        "helpeeId": "iwonAbZGTP9j7BFe3",
        "groupId": "sM3z5FkZfsABqcj3g",
        "value": 0
    },
    {
        "_id": "RJ89WSH9fKpytFMpt",
        "helperId": "N3LsK5NJeKm8PkBx8",
        "helpeeId": "zn7csxv966BaTnhrg",
        "groupId": "sM3z5FkZfsABqcj3g",
        "value": 0.33
    },
    {
        "_id": "whxEn2wF5eZPDecD5",
        "helperId": "afyZT6q2HepoCS76m",
        "helpeeId": "aupdNzYu8WmNEi4e5",
        "groupId": "sM3z5FkZfsABqcj3g",
        "value": 0
    },
    {
        "_id": "gFddsJe3nvoZ7dQ3K",
        "helperId": "9gcjpT4daYZmZDi2F",
        "helpeeId": "6rZbYn3cbQ9KNLRM5",
        "groupId": "sM3z5FkZfsABqcj3g",
        "value": 0.66
    },
    {
        "_id": "Gc5muM9bQEQbFAFLM",
        "helperId": "6rZbYn3cbQ9KNLRM5",
        "helpeeId": "u6DrqFSvdZnWDgjz8",
        "groupId": "sM3z5FkZfsABqcj3g",
        "value": 0
    },
    {
        "_id": "knPhDHdQRjvh2gfny",
        "helperId": "afyZT6q2HepoCS76m",
        "helpeeId": "PavTL8zD9664wvtfB",
        "groupId": "sM3z5FkZfsABqcj3g",
        "value": 0
    },
    {
        "_id": "bmxZHEcirEQpGZZn4",
        "helperId": "PavTL8zD9664wvtfB",
        "helpeeId": "zn7csxv966BaTnhrg",
        "groupId": "sM3z5FkZfsABqcj3g",
        "value": 0.66
    },
    {
        "_id": "ygfX9hrPDFGZRzt6J",
        "helperId": "CQhpnQnrAQMZhD9tM",
        "helpeeId": "nDHZGzczDWyqvyFhp",
        "groupId": "sM3z5FkZfsABqcj3g",
        "value": 0.66
    },
    {
        "_id": "rjXFCoDACEL4L7Mhw",
        "helperId": "nDHZGzczDWyqvyFhp",
        "helpeeId": "oBkvE34HKoa2MaDme",
        "groupId": "sM3z5FkZfsABqcj3g",
        "value": -1
    },
    {
        "_id": "mnihdBeJyNMARtLiz",
        "helperId": "aupdNzYu8WmNEi4e5",
        "helpeeId": "oBkvE34HKoa2MaDme",
        "groupId": "sM3z5FkZfsABqcj3g",
        "value": -1
    },
    {
        "_id": "w9cCPpBYxnY8dyKaM",
        "helperId": "EDEFWcagLwCfXP5Jg",
        "helpeeId": "oBkvE34HKoa2MaDme",
        "groupId": "sM3z5FkZfsABqcj3g",
        "value": -1
    },
    {
        "_id": "J8Qa3LyXZf5GScsk9",
        "helperId": "yLoAP6fd9WbQQPyhb",
        "helpeeId": "oBkvE34HKoa2MaDme",
        "groupId": "sM3z5FkZfsABqcj3g",
        "value": 1
    },
    {
        "_id": "BuJYQpb7BEqcPiJw7",
        "helperId": "9gcjpT4daYZmZDi2F",
        "helpeeId": "6Yv3ARWJQMWtFKgnN",
        "groupId": "sM3z5FkZfsABqcj3g",
        "value": 0.66
    },
    {
        "_id": "Lk5WATJLXX84cGvKR",
        "helperId": "PavTL8zD9664wvtfB",
        "helpeeId": "oBkvE34HKoa2MaDme",
        "groupId": "sM3z5FkZfsABqcj3g",
        "value": 0.66
    },
    {
        "_id": "QAJ3J3xGTA8kzHi4h",
        "helperId": "oBkvE34HKoa2MaDme",
        "helpeeId": "9zFPYRJQ5KnGTcnMr",
        "groupId": "sM3z5FkZfsABqcj3g",
        "value": 0.33
    },
    {
        "_id": "K3gJ4JHsLLnNTWqiu",
        "helperId": "PavTL8zD9664wvtfB",
        "helpeeId": "XjH8WJxEXFgTwdi3o",
        "groupId": "sM3z5FkZfsABqcj3g",
        "value": 0
    },
    {
        "_id": "BoAFCpzBFv6SrLMta",
        "helperId": "9zFPYRJQ5KnGTcnMr",
        "helpeeId": "oBkvE34HKoa2MaDme",
        "groupId": "sM3z5FkZfsABqcj3g",
        "value": 0.33
    },
    {
        "_id": "Ne9xomekqaW8Cv54L",
        "helperId": "9gcjpT4daYZmZDi2F",
        "helpeeId": "N3LsK5NJeKm8PkBx8",
        "groupId": "sM3z5FkZfsABqcj3g",
        "value": 0.33
    },
    {
        "_id": "JNAGpCpCHypsXnXRt",
        "helperId": "PavTL8zD9664wvtfB",
        "helpeeId": "yLoAP6fd9WbQQPyhb",
        "groupId": "sM3z5FkZfsABqcj3g",
        "value": 0.66
    },
    {
        "_id": "porXQrcJHxcXGhKAp",
        "helperId": "CQhpnQnrAQMZhD9tM",
        "helpeeId": "iwonAbZGTP9j7BFe3",
        "groupId": "sM3z5FkZfsABqcj3g",
        "value": 0.33
    },
    {
        "_id": "iAZCDR9KvYgQB7wJx",
        "helperId": "6rZbYn3cbQ9KNLRM5",
        "helpeeId": "oBkvE34HKoa2MaDme",
        "groupId": "sM3z5FkZfsABqcj3g",
        "value": 0
    },
    {
        "_id": "74eHE4pLfGpnWFBH8",
        "helperId": "oBkvE34HKoa2MaDme",
        "helpeeId": "EDEFWcagLwCfXP5Jg",
        "groupId": "sM3z5FkZfsABqcj3g",
        "value": 0
    },
    {
        "_id": "vubpk4xDaR6kaJW5w",
        "helperId": "CQhpnQnrAQMZhD9tM",
        "helpeeId": "6rZbYn3cbQ9KNLRM5",
        "groupId": "sM3z5FkZfsABqcj3g",
        "value": 1
    },
    {
        "_id": "mKrKx2YaApDvFvYyo",
        "helperId": "zn7csxv966BaTnhrg",
        "helpeeId": "EDEFWcagLwCfXP5Jg",
        "groupId": "sM3z5FkZfsABqcj3g",
        "value": 0.66
    },
    {
        "_id": "2YFZ2ZNvcpLD9n4xi",
        "helperId": "oBkvE34HKoa2MaDme",
        "helpeeId": "nDHZGzczDWyqvyFhp",
        "groupId": "sM3z5FkZfsABqcj3g",
        "value": 0.33
    },
    {
        "_id": "5Dc4QWoKjWFS9aWGR",
        "helperId": "CQhpnQnrAQMZhD9tM",
        "helpeeId": "6Yv3ARWJQMWtFKgnN",
        "groupId": "sM3z5FkZfsABqcj3g",
        "value": 0.66
    },
    {
        "_id": "JbQjJ8BAejFNSntSG",
        "helperId": "zn7csxv966BaTnhrg",
        "helpeeId": "nDHZGzczDWyqvyFhp",
        "groupId": "sM3z5FkZfsABqcj3g",
        "value": 0.66
    },
    {
        "_id": "cifinyjkq7vQ8uRkh",
        "helperId": "iwonAbZGTP9j7BFe3",
        "helpeeId": "oBkvE34HKoa2MaDme",
        "groupId": "sM3z5FkZfsABqcj3g",
        "value": 0
    },
    {
        "_id": "2C6NPcHodLNHG5km8",
        "helperId": "zn7csxv966BaTnhrg",
        "helpeeId": "dZ23LYG2G42mY3NAf",
        "groupId": "sM3z5FkZfsABqcj3g",
        "value": 0.33
    },
    {
        "_id": "ztzKYR5vhe2PoPDdS",
        "helperId": "oBkvE34HKoa2MaDme",
        "helpeeId": "dZ23LYG2G42mY3NAf",
        "groupId": "sM3z5FkZfsABqcj3g",
        "value": 0
    },
    {
        "_id": "N75ZxAhAKELSqnyi5",
        "helperId": "oBkvE34HKoa2MaDme",
        "helpeeId": "aupdNzYu8WmNEi4e5",
        "groupId": "sM3z5FkZfsABqcj3g",
        "value": 0.33
    },
    {
        "_id": "uh2FXGn4PWDt4A4mN",
        "helperId": "zn7csxv966BaTnhrg",
        "helpeeId": "aupdNzYu8WmNEi4e5",
        "groupId": "sM3z5FkZfsABqcj3g",
        "value": 0.66
    },
    {
        "_id": "8pJoh89FryWf6uys7",
        "helperId": "9gcjpT4daYZmZDi2F",
        "helpeeId": "zn7csxv966BaTnhrg",
        "groupId": "sM3z5FkZfsABqcj3g",
        "value": 0.33
    },
    {
        "_id": "SNqfPqMngqjgupMKu",
        "helperId": "oBkvE34HKoa2MaDme",
        "helpeeId": "PavTL8zD9664wvtfB",
        "groupId": "sM3z5FkZfsABqcj3g",
        "value": 0.33
    },
    {
        "_id": "QXAiM2wdMLLKew7hy",
        "helperId": "CQhpnQnrAQMZhD9tM",
        "helpeeId": "u6DrqFSvdZnWDgjz8",
        "groupId": "sM3z5FkZfsABqcj3g",
        "value": 0.66
    },
    {
        "_id": "sNsqtXJpEQ5nzq2jz",
        "helperId": "zn7csxv966BaTnhrg",
        "helpeeId": "PavTL8zD9664wvtfB",
        "groupId": "sM3z5FkZfsABqcj3g",
        "value": 0
    },
    {
        "_id": "KYbKs5SoMc4SxB7Eq",
        "helperId": "zn7csxv966BaTnhrg",
        "helpeeId": "6rZbYn3cbQ9KNLRM5",
        "groupId": "sM3z5FkZfsABqcj3g",
        "value": 0.66
    },
    {
        "_id": "4qgNXQJ6AMaPsW3xR",
        "helperId": "9gcjpT4daYZmZDi2F",
        "helpeeId": "CQhpnQnrAQMZhD9tM",
        "groupId": "sM3z5FkZfsABqcj3g",
        "value": 0.33
    },
    {
        "_id": "GYaA4gd3HQNdvmdju",
        "helperId": "zn7csxv966BaTnhrg",
        "helpeeId": "iwonAbZGTP9j7BFe3",
        "groupId": "sM3z5FkZfsABqcj3g",
        "value": 0.66
    },
    {
        "_id": "zkuhgoAMJEaHusty7",
        "helperId": "XjH8WJxEXFgTwdi3o",
        "helpeeId": "oBkvE34HKoa2MaDme",
        "groupId": "sM3z5FkZfsABqcj3g",
        "value": 0.33
    },
    {
        "_id": "yjR3ygS3YPAZsQCqB",
        "helperId": "oBkvE34HKoa2MaDme",
        "helpeeId": "zn7csxv966BaTnhrg",
        "groupId": "sM3z5FkZfsABqcj3g",
        "value": 0.33
    },
    {
        "_id": "vEnoC9QMiRnkTRrih",
        "helperId": "CQhpnQnrAQMZhD9tM",
        "helpeeId": "N3LsK5NJeKm8PkBx8",
        "groupId": "sM3z5FkZfsABqcj3g",
        "value": -1
    },
    {
        "_id": "a5CbqDwfdoMzPPeni",
        "helperId": "9gcjpT4daYZmZDi2F",
        "helpeeId": "oBkvE34HKoa2MaDme",
        "groupId": "sM3z5FkZfsABqcj3g",
        "value": 0.33
    },
    {
        "_id": "Hsyv4yopanN8FKi3i",
        "helperId": "afyZT6q2HepoCS76m",
        "helpeeId": "9zFPYRJQ5KnGTcnMr",
        "groupId": "sM3z5FkZfsABqcj3g",
        "value": -1
    },
    {
        "_id": "KzxwHYTeCsmSQM5SD",
        "helperId": "EDEFWcagLwCfXP5Jg",
        "helpeeId": "afyZT6q2HepoCS76m",
        "groupId": "sM3z5FkZfsABqcj3g",
        "value": -1
    },
    {
        "_id": "jYsMN2GrwkDMueaZx",
        "helperId": "EDEFWcagLwCfXP5Jg",
        "helpeeId": "9zFPYRJQ5KnGTcnMr",
        "groupId": "sM3z5FkZfsABqcj3g",
        "value": -1
    },
    {
        "_id": "KbiwJ6WstPohtk27m",
        "helperId": "afyZT6q2HepoCS76m",
        "helpeeId": "EDEFWcagLwCfXP5Jg",
        "groupId": "sM3z5FkZfsABqcj3g",
        "value": 0
    },
    {
        "_id": "JDbrRhKEG3Q6aiPdi",
        "helperId": "EDEFWcagLwCfXP5Jg",
        "helpeeId": "nDHZGzczDWyqvyFhp",
        "groupId": "sM3z5FkZfsABqcj3g",
        "value": 0
    },
    {
        "_id": "oPZsHqEocHWPTBtAE",
        "helperId": "afyZT6q2HepoCS76m",
        "helpeeId": "dZ23LYG2G42mY3NAf",
        "groupId": "sM3z5FkZfsABqcj3g",
        "value": -1
    },
    {
        "_id": "ZnShqKKkYZbDLSYqJ",
        "helperId": "nDHZGzczDWyqvyFhp",
        "helpeeId": "dZ23LYG2G42mY3NAf",
        "groupId": "sM3z5FkZfsABqcj3g",
        "value": -1
    },
    {
        "_id": "vzwvErZPbkGBnHoJF",
        "helperId": "EDEFWcagLwCfXP5Jg",
        "helpeeId": "dZ23LYG2G42mY3NAf",
        "groupId": "sM3z5FkZfsABqcj3g",
        "value": 0
    },
    {
        "_id": "tmdekTSmuh8cpegbP",
        "helperId": "dZ23LYG2G42mY3NAf",
        "helpeeId": "nDHZGzczDWyqvyFhp",
        "groupId": "sM3z5FkZfsABqcj3g",
        "value": 1
    },
    {
        "_id": "h8jAJpWSsPPW97t2Y",
        "helperId": "dZ23LYG2G42mY3NAf",
        "helpeeId": "9zFPYRJQ5KnGTcnMr",
        "groupId": "sM3z5FkZfsABqcj3g",
        "value": -1
    },
    {
        "_id": "geAFkC3BHqSPP9Xnq",
        "helperId": "dZ23LYG2G42mY3NAf",
        "helpeeId": "afyZT6q2HepoCS76m",
        "groupId": "sM3z5FkZfsABqcj3g",
        "value": -1
    },
    {
        "_id": "LvJa5Gogwxuv7vt2P",
        "helperId": "nDHZGzczDWyqvyFhp",
        "helpeeId": "aupdNzYu8WmNEi4e5",
        "groupId": "sM3z5FkZfsABqcj3g",
        "value": 1
    },
    {
        "_id": "MtuCQoogzYaxf46G8",
        "helperId": "nDHZGzczDWyqvyFhp",
        "helpeeId": "EDEFWcagLwCfXP5Jg",
        "groupId": "sM3z5FkZfsABqcj3g",
        "value": -1
    },
    {
        "_id": "dwaTmKNu6xuPTj5Bm",
        "helperId": "nDHZGzczDWyqvyFhp",
        "helpeeId": "9zFPYRJQ5KnGTcnMr",
        "groupId": "sM3z5FkZfsABqcj3g",
        "value": -1
    },
    {
        "_id": "CCDa4TreZTthJmDHr",
        "helperId": "nDHZGzczDWyqvyFhp",
        "helpeeId": "afyZT6q2HepoCS76m",
        "groupId": "sM3z5FkZfsABqcj3g",
        "value": -1
    },
    {
        "_id": "ioMpcDpdMeix8LWeQ",
        "helperId": "aupdNzYu8WmNEi4e5",
        "helpeeId": "afyZT6q2HepoCS76m",
        "groupId": "sM3z5FkZfsABqcj3g",
        "value": -1
    },
    {
        "_id": "AyooWwPQCzxjh6SAq",
        "helperId": "EDEFWcagLwCfXP5Jg",
        "helpeeId": "aupdNzYu8WmNEi4e5",
        "groupId": "sM3z5FkZfsABqcj3g",
        "value": 1
    },
    {
        "_id": "hDRwpr9LCwbmnBY3g",
        "helperId": "aupdNzYu8WmNEi4e5",
        "helpeeId": "9zFPYRJQ5KnGTcnMr",
        "groupId": "sM3z5FkZfsABqcj3g",
        "value": -1
    },
    {
        "_id": "xkP27SHDdSF9ewtiF",
        "helperId": "aupdNzYu8WmNEi4e5",
        "helpeeId": "EDEFWcagLwCfXP5Jg",
        "groupId": "sM3z5FkZfsABqcj3g",
        "value": -1
    },
    {
        "_id": "CDBopFC7Q8jQzyZAC",
        "helperId": "PavTL8zD9664wvtfB",
        "helpeeId": "afyZT6q2HepoCS76m",
        "groupId": "sM3z5FkZfsABqcj3g",
        "value": -1
    },
    {
        "_id": "Js5GFxQ3z3doPtNDj",
        "helperId": "dZ23LYG2G42mY3NAf",
        "helpeeId": "EDEFWcagLwCfXP5Jg",
        "groupId": "sM3z5FkZfsABqcj3g",
        "value": -1
    },
    {
        "_id": "SaCb5SmWeYprn9Ha7",
        "helperId": "EDEFWcagLwCfXP5Jg",
        "helpeeId": "PavTL8zD9664wvtfB",
        "groupId": "sM3z5FkZfsABqcj3g",
        "value": 0
    },
    {
        "_id": "mLZZHmi99QxwQAQW4",
        "helperId": "dZ23LYG2G42mY3NAf",
        "helpeeId": "PavTL8zD9664wvtfB",
        "groupId": "sM3z5FkZfsABqcj3g",
        "value": -1
    },
    {
        "_id": "55ZMqm4PBTYFpijYg",
        "helperId": "aupdNzYu8WmNEi4e5",
        "helpeeId": "nDHZGzczDWyqvyFhp",
        "groupId": "sM3z5FkZfsABqcj3g",
        "value": 1
    },
    {
        "_id": "2fxxZsYkHtA96wPiP",
        "helperId": "EDEFWcagLwCfXP5Jg",
        "helpeeId": "iwonAbZGTP9j7BFe3",
        "groupId": "sM3z5FkZfsABqcj3g",
        "value": -1
    },
    {
        "_id": "Lq8dyKqFNe6k8vJZe",
        "helperId": "dZ23LYG2G42mY3NAf",
        "helpeeId": "iwonAbZGTP9j7BFe3",
        "groupId": "sM3z5FkZfsABqcj3g",
        "value": -1
    },
    {
        "_id": "TkweGkMAsmQJhmtaR",
        "helperId": "dZ23LYG2G42mY3NAf",
        "helpeeId": "aupdNzYu8WmNEi4e5",
        "groupId": "sM3z5FkZfsABqcj3g",
        "value": 0.33
    },
    {
        "_id": "wwzdxXgdZjdmsGLmf",
        "helperId": "nDHZGzczDWyqvyFhp",
        "helpeeId": "PavTL8zD9664wvtfB",
        "groupId": "sM3z5FkZfsABqcj3g",
        "value": -1
    },
    {
        "_id": "D4qdhirjqQMyKCN9s",
        "helperId": "nDHZGzczDWyqvyFhp",
        "helpeeId": "iwonAbZGTP9j7BFe3",
        "groupId": "sM3z5FkZfsABqcj3g",
        "value": -1
    },
    {
        "_id": "A8y7BTnQJii7J2GGJ",
        "helperId": "aupdNzYu8WmNEi4e5",
        "helpeeId": "dZ23LYG2G42mY3NAf",
        "groupId": "sM3z5FkZfsABqcj3g",
        "value": -1
    },
    {
        "_id": "aZbJ8M5HK4h9eQxsw",
        "helperId": "aupdNzYu8WmNEi4e5",
        "helpeeId": "PavTL8zD9664wvtfB",
        "groupId": "sM3z5FkZfsABqcj3g",
        "value": -1
    },
    {
        "_id": "hQhWkwnDPh8ksTmmm",
        "helperId": "aupdNzYu8WmNEi4e5",
        "helpeeId": "iwonAbZGTP9j7BFe3",
        "groupId": "sM3z5FkZfsABqcj3g",
        "value": -1
    },
    {
        "_id": "a2KjS6EX3gHtgSztj",
        "helperId": "EDEFWcagLwCfXP5Jg",
        "helpeeId": "6rZbYn3cbQ9KNLRM5",
        "groupId": "sM3z5FkZfsABqcj3g",
        "value": 0.66
    },
    {
        "_id": "vWPrEWtG2tjiqj5Ja",
        "helperId": "aupdNzYu8WmNEi4e5",
        "helpeeId": "6rZbYn3cbQ9KNLRM5",
        "groupId": "sM3z5FkZfsABqcj3g",
        "value": 0
    },
    {
        "_id": "vkP5fo3zvnSncFLcn",
        "helperId": "iwonAbZGTP9j7BFe3",
        "helpeeId": "afyZT6q2HepoCS76m",
        "groupId": "sM3z5FkZfsABqcj3g",
        "value": -1
    },
    {
        "_id": "gd5ofjXRwCQuSZp96",
        "helperId": "PavTL8zD9664wvtfB",
        "helpeeId": "9zFPYRJQ5KnGTcnMr",
        "groupId": "sM3z5FkZfsABqcj3g",
        "value": 0.33
    },
    {
        "_id": "h54yTu2h7DRpyz4Dx",
        "helperId": "dZ23LYG2G42mY3NAf",
        "helpeeId": "6rZbYn3cbQ9KNLRM5",
        "groupId": "sM3z5FkZfsABqcj3g",
        "value": 0.33
    },
    {
        "_id": "KAuAjZtm6NfYDnxuY",
        "helperId": "iwonAbZGTP9j7BFe3",
        "helpeeId": "nDHZGzczDWyqvyFhp",
        "groupId": "sM3z5FkZfsABqcj3g",
        "value": 1
    },
    {
        "_id": "bqD2pbThbqTDYwC9W",
        "helperId": "EDEFWcagLwCfXP5Jg",
        "helpeeId": "6Yv3ARWJQMWtFKgnN",
        "groupId": "sM3z5FkZfsABqcj3g",
        "value": -1
    },
    {
        "_id": "cZ2G6AkdRweBkfhZE",
        "helperId": "aupdNzYu8WmNEi4e5",
        "helpeeId": "6Yv3ARWJQMWtFKgnN",
        "groupId": "sM3z5FkZfsABqcj3g",
        "value": -1
    },
    {
        "_id": "B8NEip8zuWcbk9quL",
        "helperId": "iwonAbZGTP9j7BFe3",
        "helpeeId": "dZ23LYG2G42mY3NAf",
        "groupId": "sM3z5FkZfsABqcj3g",
        "value": 0.66
    },
    {
        "_id": "vJ4hkhfMkmq585ASg",
        "helperId": "afyZT6q2HepoCS76m",
        "helpeeId": "6Yv3ARWJQMWtFKgnN",
        "groupId": "sM3z5FkZfsABqcj3g",
        "value": 0.66
    },
    {
        "_id": "8Fjps3TrXLPq6fAYK",
        "helperId": "6Yv3ARWJQMWtFKgnN",
        "helpeeId": "9zFPYRJQ5KnGTcnMr",
        "groupId": "sM3z5FkZfsABqcj3g",
        "value": 0.66
    },
    {
        "_id": "y7gEibQo38FkdSgbj",
        "helperId": "6Yv3ARWJQMWtFKgnN",
        "helpeeId": "EDEFWcagLwCfXP5Jg",
        "groupId": "sM3z5FkZfsABqcj3g",
        "value": -1
    },
    {
        "_id": "3je7CiyhJFSSPeWZo",
        "helperId": "6Yv3ARWJQMWtFKgnN",
        "helpeeId": "nDHZGzczDWyqvyFhp",
        "groupId": "sM3z5FkZfsABqcj3g",
        "value": 1
    },
    {
        "_id": "QwW3WQ7unL6ea6HA9",
        "helperId": "nDHZGzczDWyqvyFhp",
        "helpeeId": "6rZbYn3cbQ9KNLRM5",
        "groupId": "sM3z5FkZfsABqcj3g",
        "value": -1
    },
    {
        "_id": "FxxojfoQGE3YzQzBE",
        "helperId": "dZ23LYG2G42mY3NAf",
        "helpeeId": "6Yv3ARWJQMWtFKgnN",
        "groupId": "sM3z5FkZfsABqcj3g",
        "value": 0.66
    },
    {
        "_id": "TfzxL9SRM8XWkhXnk",
        "helperId": "nDHZGzczDWyqvyFhp",
        "helpeeId": "6Yv3ARWJQMWtFKgnN",
        "groupId": "sM3z5FkZfsABqcj3g",
        "value": -1
    },
    {
        "_id": "LwuJz8YosSLzaNrsk",
        "helperId": "6rZbYn3cbQ9KNLRM5",
        "helpeeId": "nDHZGzczDWyqvyFhp",
        "groupId": "sM3z5FkZfsABqcj3g",
        "value": 1
    },
    {
        "_id": "dPwpfjw5PPEp3yECN",
        "helperId": "iwonAbZGTP9j7BFe3",
        "helpeeId": "9zFPYRJQ5KnGTcnMr",
        "groupId": "sM3z5FkZfsABqcj3g",
        "value": 0.66
    },
    {
        "_id": "JE7hQ77gcTeP5JMGF",
        "helperId": "iwonAbZGTP9j7BFe3",
        "helpeeId": "EDEFWcagLwCfXP5Jg",
        "groupId": "sM3z5FkZfsABqcj3g",
        "value": 0
    },
    {
        "_id": "Evx2TWG8dZjo4goth",
        "helperId": "6Yv3ARWJQMWtFKgnN",
        "helpeeId": "dZ23LYG2G42mY3NAf",
        "groupId": "sM3z5FkZfsABqcj3g",
        "value": 0.66
    },
    {
        "_id": "QEMcyLck8DxpWY6gE",
        "helperId": "PavTL8zD9664wvtfB",
        "helpeeId": "EDEFWcagLwCfXP5Jg",
        "groupId": "sM3z5FkZfsABqcj3g",
        "value": -1
    },
    {
        "_id": "doyxXziA44ekop2GT",
        "helperId": "6Yv3ARWJQMWtFKgnN",
        "helpeeId": "aupdNzYu8WmNEi4e5",
        "groupId": "sM3z5FkZfsABqcj3g",
        "value": -1
    },
    {
        "_id": "jyoM2izDdhwh8LuT2",
        "helperId": "9zFPYRJQ5KnGTcnMr",
        "helpeeId": "afyZT6q2HepoCS76m",
        "groupId": "sM3z5FkZfsABqcj3g",
        "value": -1
    },
    {
        "_id": "HxKyEWGBbnujLf58c",
        "helperId": "6rZbYn3cbQ9KNLRM5",
        "helpeeId": "6Yv3ARWJQMWtFKgnN",
        "groupId": "sM3z5FkZfsABqcj3g",
        "value": 0
    },
    {
        "_id": "RERhrZ4npHkgMEk65",
        "helperId": "iwonAbZGTP9j7BFe3",
        "helpeeId": "6Yv3ARWJQMWtFKgnN",
        "groupId": "sM3z5FkZfsABqcj3g",
        "value": -1
    },
    {
        "_id": "tBs77euEbF7HgrZtJ",
        "helperId": "6rZbYn3cbQ9KNLRM5",
        "helpeeId": "iwonAbZGTP9j7BFe3",
        "groupId": "sM3z5FkZfsABqcj3g",
        "value": 0
    },
    {
        "_id": "7rTJFjQ9Pvihz84ir",
        "helperId": "EDEFWcagLwCfXP5Jg",
        "helpeeId": "u6DrqFSvdZnWDgjz8",
        "groupId": "sM3z5FkZfsABqcj3g",
        "value": 0.66
    },
    {
        "_id": "X555NiwxQjJzefYX7",
        "helperId": "aupdNzYu8WmNEi4e5",
        "helpeeId": "u6DrqFSvdZnWDgjz8",
        "groupId": "sM3z5FkZfsABqcj3g",
        "value": 0
    },
    {
        "_id": "ispwehT6yiisRqfMw",
        "helperId": "EDEFWcagLwCfXP5Jg",
        "helpeeId": "9gcjpT4daYZmZDi2F",
        "groupId": "sM3z5FkZfsABqcj3g",
        "value": -1
    },
    {
        "_id": "CahQPrWZJdBJjGmWw",
        "helperId": "aupdNzYu8WmNEi4e5",
        "helpeeId": "XjH8WJxEXFgTwdi3o",
        "groupId": "sM3z5FkZfsABqcj3g",
        "value": -1
    },
    {
        "_id": "iLkNxkoxfR9Jgws2n",
        "helperId": "9zFPYRJQ5KnGTcnMr",
        "helpeeId": "EDEFWcagLwCfXP5Jg",
        "groupId": "sM3z5FkZfsABqcj3g",
        "value": 0
    },
    {
        "_id": "vGo3TosMTZ4g9Yofs",
        "helperId": "aupdNzYu8WmNEi4e5",
        "helpeeId": "yLoAP6fd9WbQQPyhb",
        "groupId": "sM3z5FkZfsABqcj3g",
        "value": -1
    },
    {
        "_id": "Pyr6G2jwB8EgQjeLb",
        "helperId": "EDEFWcagLwCfXP5Jg",
        "helpeeId": "XjH8WJxEXFgTwdi3o",
        "groupId": "sM3z5FkZfsABqcj3g",
        "value": -1
    },
    {
        "_id": "NuzX4pcXdZr4qgcXX",
        "helperId": "u6DrqFSvdZnWDgjz8",
        "helpeeId": "afyZT6q2HepoCS76m",
        "groupId": "sM3z5FkZfsABqcj3g",
        "value": -1
    },
    {
        "_id": "CpZYa7sjWncWEr9q6",
        "helperId": "afyZT6q2HepoCS76m",
        "helpeeId": "iwonAbZGTP9j7BFe3",
        "groupId": "sM3z5FkZfsABqcj3g",
        "value": 0.66
    },
    {
        "_id": "Kb9HvGQuRnYbnRdFx",
        "helperId": "yLoAP6fd9WbQQPyhb",
        "helpeeId": "afyZT6q2HepoCS76m",
        "groupId": "sM3z5FkZfsABqcj3g",
        "value": 0.66
    },
    {
        "_id": "k4BKRk9dn7DLXWxTr",
        "helperId": "dZ23LYG2G42mY3NAf",
        "helpeeId": "yLoAP6fd9WbQQPyhb",
        "groupId": "sM3z5FkZfsABqcj3g",
        "value": 0.66
    },
    {
        "_id": "h7hXNQPGoMHisoXPf",
        "helperId": "9zFPYRJQ5KnGTcnMr",
        "helpeeId": "nDHZGzczDWyqvyFhp",
        "groupId": "sM3z5FkZfsABqcj3g",
        "value": 1
    },
    {
        "_id": "pg5bFHMpjj4kZj3yo",
        "helperId": "EDEFWcagLwCfXP5Jg",
        "helpeeId": "yLoAP6fd9WbQQPyhb",
        "groupId": "sM3z5FkZfsABqcj3g",
        "value": 0
    },
    {
        "_id": "kPJuCTCxNuwHvA9Gu",
        "helperId": "nDHZGzczDWyqvyFhp",
        "helpeeId": "zn7csxv966BaTnhrg",
        "groupId": "sM3z5FkZfsABqcj3g",
        "value": -1
    },
    {
        "_id": "Lj2NsLJCx9WSSw2Xv",
        "helperId": "dZ23LYG2G42mY3NAf",
        "helpeeId": "zn7csxv966BaTnhrg",
        "groupId": "sM3z5FkZfsABqcj3g",
        "value": -1
    },
    {
        "_id": "beJkRybkYMJYdTWLq",
        "helperId": "N3LsK5NJeKm8PkBx8",
        "helpeeId": "iwonAbZGTP9j7BFe3",
        "groupId": "sM3z5FkZfsABqcj3g",
        "value": -1
    },
    {
        "_id": "WP2vaZNzedTngJtJ3",
        "helperId": "9zFPYRJQ5KnGTcnMr",
        "helpeeId": "u6DrqFSvdZnWDgjz8",
        "groupId": "sM3z5FkZfsABqcj3g",
        "value": 0.33
    },
    {
        "_id": "4E5XrRx9eKL9JA5Fi",
        "helperId": "afyZT6q2HepoCS76m",
        "helpeeId": "9gcjpT4daYZmZDi2F",
        "groupId": "sM3z5FkZfsABqcj3g",
        "value": 0
    },
    {
        "_id": "JKdQKTNQ7ThBrS6xg",
        "helperId": "N3LsK5NJeKm8PkBx8",
        "helpeeId": "6rZbYn3cbQ9KNLRM5",
        "groupId": "sM3z5FkZfsABqcj3g",
        "value": 1
    },
    {
        "_id": "FDsRxe3wet8YYkTdR",
        "helperId": "6Yv3ARWJQMWtFKgnN",
        "helpeeId": "zn7csxv966BaTnhrg",
        "groupId": "sM3z5FkZfsABqcj3g",
        "value": 1
    },
    {
        "_id": "Z2AGAz66zDhWDcu9X",
        "helperId": "6rZbYn3cbQ9KNLRM5",
        "helpeeId": "N3LsK5NJeKm8PkBx8",
        "groupId": "sM3z5FkZfsABqcj3g",
        "value": 0
    },
    {
        "_id": "verxHpWRP9SgatoZs",
        "helperId": "N3LsK5NJeKm8PkBx8",
        "helpeeId": "6Yv3ARWJQMWtFKgnN",
        "groupId": "sM3z5FkZfsABqcj3g",
        "value": 1
    },
    {
        "_id": "dKkTAMXBJwFkA2wPx",
        "helperId": "iwonAbZGTP9j7BFe3",
        "helpeeId": "9gcjpT4daYZmZDi2F",
        "groupId": "sM3z5FkZfsABqcj3g",
        "value": -1
    },
    {
        "_id": "e3dE6WYu34HK7vwpi",
        "helperId": "9zFPYRJQ5KnGTcnMr",
        "helpeeId": "9gcjpT4daYZmZDi2F",
        "groupId": "sM3z5FkZfsABqcj3g",
        "value": 0
    },
    {
        "_id": "rCjiPCcAxTZvvzZcm",
        "helperId": "N3LsK5NJeKm8PkBx8",
        "helpeeId": "u6DrqFSvdZnWDgjz8",
        "groupId": "sM3z5FkZfsABqcj3g",
        "value": 0.66
    },
    {
        "_id": "qhTbTm6kuWHkzsrAu",
        "helperId": "XjH8WJxEXFgTwdi3o",
        "helpeeId": "6Yv3ARWJQMWtFKgnN",
        "groupId": "sM3z5FkZfsABqcj3g",
        "value": 0.66
    },
    {
        "_id": "M5rB75rS5Gh8bJ9ko",
        "helperId": "yLoAP6fd9WbQQPyhb",
        "helpeeId": "PavTL8zD9664wvtfB",
        "groupId": "sM3z5FkZfsABqcj3g",
        "value": 0.66
    },
    {
        "_id": "XPf7Ac3oWdCFR2HRr",
        "helperId": "9gcjpT4daYZmZDi2F",
        "helpeeId": "afyZT6q2HepoCS76m",
        "groupId": "sM3z5FkZfsABqcj3g",
        "value": 0.33
    },
    {
        "_id": "DJHXdZ2AZY3khMA8j",
        "helperId": "iwonAbZGTP9j7BFe3",
        "helpeeId": "u6DrqFSvdZnWDgjz8",
        "groupId": "sM3z5FkZfsABqcj3g",
        "value": 0
    },
    {
        "_id": "NYSFNCfzjgD73WK6Y",
        "helperId": "9zFPYRJQ5KnGTcnMr",
        "helpeeId": "XjH8WJxEXFgTwdi3o",
        "groupId": "sM3z5FkZfsABqcj3g",
        "value": 0
    },
    {
        "_id": "6GnC4EpepHnnauj2i",
        "helperId": "6rZbYn3cbQ9KNLRM5",
        "helpeeId": "zn7csxv966BaTnhrg",
        "groupId": "sM3z5FkZfsABqcj3g",
        "value": 0
    },
    {
        "_id": "8mPHPecxk6ejfYLRm",
        "helperId": "XjH8WJxEXFgTwdi3o",
        "helpeeId": "u6DrqFSvdZnWDgjz8",
        "groupId": "sM3z5FkZfsABqcj3g",
        "value": -1
    },
    {
        "_id": "vwqDaGJmKxQmWwbfq",
        "helperId": "N3LsK5NJeKm8PkBx8",
        "helpeeId": "9gcjpT4daYZmZDi2F",
        "groupId": "sM3z5FkZfsABqcj3g",
        "value": 0
    },
    {
        "_id": "qNcDqs2mK7Wdg4YLu",
        "helperId": "afyZT6q2HepoCS76m",
        "helpeeId": "XjH8WJxEXFgTwdi3o",
        "groupId": "sM3z5FkZfsABqcj3g",
        "value": 0.33
    },
    {
        "_id": "tcCMu6m6fcKtZujSC",
        "helperId": "u6DrqFSvdZnWDgjz8",
        "helpeeId": "iwonAbZGTP9j7BFe3",
        "groupId": "sM3z5FkZfsABqcj3g",
        "value": 0.33
    },
    {
        "_id": "HNQzY7kSmAqDMn877",
        "helperId": "XjH8WJxEXFgTwdi3o",
        "helpeeId": "9gcjpT4daYZmZDi2F",
        "groupId": "sM3z5FkZfsABqcj3g",
        "value": 0.33
    },
    {
        "_id": "i96PdDd4q4bAzHcEg",
        "helperId": "6rZbYn3cbQ9KNLRM5",
        "helpeeId": "yLoAP6fd9WbQQPyhb",
        "groupId": "sM3z5FkZfsABqcj3g",
        "value": 0
    },
    {
        "_id": "7GQZhy5ukaec6Bu9D",
        "helperId": "6rZbYn3cbQ9KNLRM5",
        "helpeeId": "XjH8WJxEXFgTwdi3o",
        "groupId": "sM3z5FkZfsABqcj3g",
        "value": 0
    },
    {
        "_id": "k3A5WBwvrikcyN8Zc",
        "helperId": "N3LsK5NJeKm8PkBx8",
        "helpeeId": "XjH8WJxEXFgTwdi3o",
        "groupId": "sM3z5FkZfsABqcj3g",
        "value": 0.66
    },
    {
        "_id": "2H4WYro7i3DQ4K8NW",
        "helperId": "XjH8WJxEXFgTwdi3o",
        "helpeeId": "yLoAP6fd9WbQQPyhb",
        "groupId": "sM3z5FkZfsABqcj3g",
        "value": 0.33
    },
    {
        "_id": "gaadJNqdtCD7G8Yz5",
        "helperId": "u6DrqFSvdZnWDgjz8",
        "helpeeId": "6rZbYn3cbQ9KNLRM5",
        "groupId": "sM3z5FkZfsABqcj3g",
        "value": 0.66
    },
    {
        "_id": "t8QNZLkLBxTxdMXrX",
        "helperId": "afyZT6q2HepoCS76m",
        "helpeeId": "yLoAP6fd9WbQQPyhb",
        "groupId": "sM3z5FkZfsABqcj3g",
        "value": 0.66
    },
    {
        "_id": "M8SSQyWE8xDBDorXi",
        "helperId": "yLoAP6fd9WbQQPyhb",
        "helpeeId": "iwonAbZGTP9j7BFe3",
        "groupId": "sM3z5FkZfsABqcj3g",
        "value": 1
    },
    {
        "_id": "gotEfwtgKoty2S9SK",
        "helperId": "XjH8WJxEXFgTwdi3o",
        "helpeeId": "N3LsK5NJeKm8PkBx8",
        "groupId": "sM3z5FkZfsABqcj3g",
        "value": 0.66
    },
    {
        "_id": "PRiGSJfCfrRuP5swb",
        "helperId": "9gcjpT4daYZmZDi2F",
        "helpeeId": "9zFPYRJQ5KnGTcnMr",
        "groupId": "sM3z5FkZfsABqcj3g",
        "value": 1
    },
    {
        "_id": "iSbnJr34uanDDyZZT",
        "helperId": "N3LsK5NJeKm8PkBx8",
        "helpeeId": "yLoAP6fd9WbQQPyhb",
        "groupId": "sM3z5FkZfsABqcj3g",
        "value": 0.66
    },
    {
        "_id": "nnC6Rt7beMNa7zrN8",
        "helperId": "9zFPYRJQ5KnGTcnMr",
        "helpeeId": "yLoAP6fd9WbQQPyhb",
        "groupId": "sM3z5FkZfsABqcj3g",
        "value": 0.33
    },
    {
        "_id": "ca6wQccsjb74d29Hg",
        "helperId": "u6DrqFSvdZnWDgjz8",
        "helpeeId": "6Yv3ARWJQMWtFKgnN",
        "groupId": "sM3z5FkZfsABqcj3g",
        "value": 0.66
    },
    {
        "_id": "Bt7zm7QxQRNp5mEvr",
        "helperId": "6rZbYn3cbQ9KNLRM5",
        "helpeeId": "9gcjpT4daYZmZDi2F",
        "groupId": "sM3z5FkZfsABqcj3g",
        "value": 0
    },
    {
        "_id": "32yPbFDuWAiAtKDwX",
        "helperId": "yLoAP6fd9WbQQPyhb",
        "helpeeId": "6rZbYn3cbQ9KNLRM5",
        "groupId": "sM3z5FkZfsABqcj3g",
        "value": 1
    },
    {
        "_id": "HR8v7tF8JuhymxJqC",
        "helperId": "9gcjpT4daYZmZDi2F",
        "helpeeId": "EDEFWcagLwCfXP5Jg",
        "groupId": "sM3z5FkZfsABqcj3g",
        "value": 0
    },
    {
        "_id": "m3PQYaw4P4qtPYeAP",
        "helperId": "iwonAbZGTP9j7BFe3",
        "helpeeId": "zn7csxv966BaTnhrg",
        "groupId": "sM3z5FkZfsABqcj3g",
        "value": 0
    },
    {
        "_id": "iXra9W4QXaB8sdw98",
        "helperId": "XjH8WJxEXFgTwdi3o",
        "helpeeId": "aupdNzYu8WmNEi4e5",
        "groupId": "sM3z5FkZfsABqcj3g",
        "value": 0
    },
    {
        "_id": "LsnGBzSjSbEx9KZzT",
        "helperId": "9zFPYRJQ5KnGTcnMr",
        "helpeeId": "N3LsK5NJeKm8PkBx8",
        "groupId": "sM3z5FkZfsABqcj3g",
        "value": 0
    },
    {
        "_id": "4Jep5X5XNbjasMoN2",
        "helperId": "afyZT6q2HepoCS76m",
        "helpeeId": "N3LsK5NJeKm8PkBx8",
        "groupId": "sM3z5FkZfsABqcj3g",
        "value": 0.66
    },
    {
        "_id": "u86iBeptgFtNpnKYd",
        "helperId": "yLoAP6fd9WbQQPyhb",
        "helpeeId": "6Yv3ARWJQMWtFKgnN",
        "groupId": "sM3z5FkZfsABqcj3g",
        "value": 0.66
    },
    {
        "_id": "w2yJ4iaYKtimZWCyA",
        "helperId": "EDEFWcagLwCfXP5Jg",
        "helpeeId": "CQhpnQnrAQMZhD9tM",
        "groupId": "sM3z5FkZfsABqcj3g",
        "value": -1
    },
    {
        "_id": "fTwaxEdg8hRyGTSbu",
        "helperId": "XjH8WJxEXFgTwdi3o",
        "helpeeId": "iwonAbZGTP9j7BFe3",
        "groupId": "sM3z5FkZfsABqcj3g",
        "value": 0.66
    },
    {
        "_id": "zupiHwzSohkD3Tn37",
        "helperId": "9gcjpT4daYZmZDi2F",
        "helpeeId": "nDHZGzczDWyqvyFhp",
        "groupId": "sM3z5FkZfsABqcj3g",
        "value": 0.33
    },
    {
        "_id": "ApNZGJSS9ZpsjqBFT",
        "helperId": "yLoAP6fd9WbQQPyhb",
        "helpeeId": "u6DrqFSvdZnWDgjz8",
        "groupId": "sM3z5FkZfsABqcj3g",
        "value": 0.66
    },
    {
        "_id": "5AxoZzcfTgeXCxrtR",
        "helperId": "nDHZGzczDWyqvyFhp",
        "helpeeId": "CQhpnQnrAQMZhD9tM",
        "groupId": "sM3z5FkZfsABqcj3g",
        "value": -1
    },
    {
        "_id": "98gNwjBvE7DrYFZJh",
        "helperId": "iwonAbZGTP9j7BFe3",
        "helpeeId": "CQhpnQnrAQMZhD9tM",
        "groupId": "sM3z5FkZfsABqcj3g",
        "value": 1
    },
    {
        "_id": "8g9tm57tgi8NCajEc",
        "helperId": "N3LsK5NJeKm8PkBx8",
        "helpeeId": "CQhpnQnrAQMZhD9tM",
        "groupId": "sM3z5FkZfsABqcj3g",
        "value": 1
    },
    {
        "_id": "hGsCPxqG8JctGXkpe",
        "helperId": "dZ23LYG2G42mY3NAf",
        "helpeeId": "CQhpnQnrAQMZhD9tM",
        "groupId": "sM3z5FkZfsABqcj3g",
        "value": 0.33
    },
    {
        "_id": "tmAmTD7qnDBAS3AYi",
        "helperId": "9zFPYRJQ5KnGTcnMr",
        "helpeeId": "zn7csxv966BaTnhrg",
        "groupId": "sM3z5FkZfsABqcj3g",
        "value": 0.33
    },
    {
        "_id": "FcuGo2oQeLgZXogeg",
        "helperId": "PavTL8zD9664wvtfB",
        "helpeeId": "aupdNzYu8WmNEi4e5",
        "groupId": "sM3z5FkZfsABqcj3g",
        "value": -1
    },
    {
        "_id": "p483KkjGmi5jw5Xd7",
        "helperId": "6Yv3ARWJQMWtFKgnN",
        "helpeeId": "CQhpnQnrAQMZhD9tM",
        "groupId": "sM3z5FkZfsABqcj3g",
        "value": 1
    },
    {
        "_id": "Gb8e8D85r4S8HQjTp",
        "helperId": "XjH8WJxEXFgTwdi3o",
        "helpeeId": "zn7csxv966BaTnhrg",
        "groupId": "sM3z5FkZfsABqcj3g",
        "value": 0.33
    },
    {
        "_id": "FZuyJMe5aXxKPmkvm",
        "helperId": "PavTL8zD9664wvtfB",
        "helpeeId": "CQhpnQnrAQMZhD9tM",
        "groupId": "sM3z5FkZfsABqcj3g",
        "value": -1
    },
    {
        "_id": "Nbxc6bKaiK3ziBH7E",
        "helperId": "u6DrqFSvdZnWDgjz8",
        "helpeeId": "9gcjpT4daYZmZDi2F",
        "groupId": "sM3z5FkZfsABqcj3g",
        "value": 0.33
    },
    {
        "_id": "Efbf4oyr5ptXNjPxf",
        "helperId": "dZ23LYG2G42mY3NAf",
        "helpeeId": "oBkvE34HKoa2MaDme",
        "groupId": "sM3z5FkZfsABqcj3g",
        "value": 0
    },
    {
        "_id": "rdotp4Wwe3BSCDfDb",
        "helperId": "6Yv3ARWJQMWtFKgnN",
        "helpeeId": "oBkvE34HKoa2MaDme",
        "groupId": "sM3z5FkZfsABqcj3g",
        "value": -1
    },
    {
        "_id": "FgE58TRWS5gCWTvms",
        "helperId": "afyZT6q2HepoCS76m",
        "helpeeId": "nDHZGzczDWyqvyFhp",
        "groupId": "sM3z5FkZfsABqcj3g",
        "value": 0.66
    },
    {
        "_id": "CmrMD5JhsD8nujH4w",
        "helperId": "9gcjpT4daYZmZDi2F",
        "helpeeId": "u6DrqFSvdZnWDgjz8",
        "groupId": "sM3z5FkZfsABqcj3g",
        "value": 0.33
    },
    {
        "_id": "TTdkyDFQGXNqw2Pg8",
        "helperId": "6rZbYn3cbQ9KNLRM5",
        "helpeeId": "EDEFWcagLwCfXP5Jg",
        "groupId": "sM3z5FkZfsABqcj3g",
        "value": 0
    },
    {
        "_id": "qekQv97gH8qsLCwWD",
        "helperId": "6rZbYn3cbQ9KNLRM5",
        "helpeeId": "dZ23LYG2G42mY3NAf",
        "groupId": "sM3z5FkZfsABqcj3g",
        "value": 0.33
    },
    {
        "_id": "gnqFXP3KbryAwqciJ",
        "helperId": "PavTL8zD9664wvtfB",
        "helpeeId": "N3LsK5NJeKm8PkBx8",
        "groupId": "sM3z5FkZfsABqcj3g",
        "value": 0
    },
    {
        "_id": "7aFg9ok7euobWZckN",
        "helperId": "9gcjpT4daYZmZDi2F",
        "helpeeId": "XjH8WJxEXFgTwdi3o",
        "groupId": "sM3z5FkZfsABqcj3g",
        "value": 0
    },
    {
        "_id": "Cj79dSxnS68a8wgLN",
        "helperId": "CQhpnQnrAQMZhD9tM",
        "helpeeId": "PavTL8zD9664wvtfB",
        "groupId": "sM3z5FkZfsABqcj3g",
        "value": 1
    },
    {
        "_id": "aeaXfmE9YioSuRMwZ",
        "helperId": "9gcjpT4daYZmZDi2F",
        "helpeeId": "yLoAP6fd9WbQQPyhb",
        "groupId": "sM3z5FkZfsABqcj3g",
        "value": -1
    },
    {
        "_id": "MHo4oteXFxXhGq3z9",
        "helperId": "afyZT6q2HepoCS76m",
        "helpeeId": "oBkvE34HKoa2MaDme",
        "groupId": "sM3z5FkZfsABqcj3g",
        "value": 0.66
    },
    {
        "_id": "CyuL6j2xLHhkcG2kK",
        "helperId": "oBkvE34HKoa2MaDme",
        "helpeeId": "afyZT6q2HepoCS76m",
        "groupId": "sM3z5FkZfsABqcj3g",
        "value": 0
    },
    {
        "_id": "q7f7PweusiKt3G37e",
        "helperId": "PavTL8zD9664wvtfB",
        "helpeeId": "9gcjpT4daYZmZDi2F",
        "groupId": "sM3z5FkZfsABqcj3g",
        "value": 0.66
    },
    {
        "_id": "3KMc2u7yeLirBQKq5",
        "helperId": "PavTL8zD9664wvtfB",
        "helpeeId": "u6DrqFSvdZnWDgjz8",
        "groupId": "sM3z5FkZfsABqcj3g",
        "value": 0.66
    }]
}
